{
    "profil" : [
        { "href" : "cv-imprime", "title" : "Mon nouveau CV" },
        { "href" : "portfolio", "title" : "Ma page de portfolio (en cours)" }
    ],
    "prieres" : [
        { "href" : "ex-base", "title" : "Prières de base" },
        { "href" : "chapelet", "title" : "Chapelet du rosaire" },
        { "href" : "sang", "title" : "Chapelet du précieux sang de Jésus" },
        { "href" : "misericorde", "title" : "Chapelet de la Miséricorde Divine" },
        { "href" : "plaies", "title" : "Chapelet des saintes plaies" }
    ],
    "exercices" : [
        { "href" : "ex-musical", "title" : "Cohérence cardiaque" }
    ]
}