[
    {
        "mystere" : "",
        "fruit" : "",
        "intro" : "",
        "clausules" : [
            "",
            "",
            "",
            "",
            "",
            "",
            "",
            "",
            "",
            ""
        ]
    },
    {
        "mystere" : "",
        "fruit" : "",
        "intro" : "",
        "clausules" : [
            "",
            "",
            "",
            "",
            "",
            "",
            "",
            "",
            "",
            ""
        ]
    },
    {
        "mystere" : "",
        "fruit" : "",
        "intro" : "",
        "clausules" : [
            "",
            "",
            "",
            "",
            "",
            "",
            "",
            "",
            "",
            ""
        ]
    },
    {
        "mystere" : "",
        "fruit" : "la grâce d'une bonne mort et la dévotion filiale à Marie",
        "intro" : " ",
        "clausules" : [
            "",
            "",
            "",
            "",
            "",
            "",
            "",
            "",
            "",
            ""
        ]
    },
    {
        "mystere" : "",
        "fruit" : "",
        "intro" : "",
        "clausules" : [
            "",
            "",
            "",
            "",
            "",
            "",
            "",
            "",
            "",
            ""
        ]
    }
]